sirex/__init__.py
sirex/file.py
sirex/future_release.py
sirex/numeric.py
sirex/string.py
sirex/utils.py
sirex-0.1.0.dist-info/METADATA
sirex-0.1.0.dist-info/RECORD
sirex-0.1.0.dist-info/WHEEL
sirex-0.1.0.dist-info/top_level.txt
