Metadata-Version: 2.1
Name: sirex
Version: 0.1.0
Summary: Simple Regex - A package to use regex commands on strings using simple function calls
Home-page: https://github.com/pythoslabs/sirex
Author: Pythos Labs
Author-email: pythoslabs@gmail.com
License: MIT
Platform: UNKNOWN
Classifier: License :: OSI Approved :: MIT License
Classifier: Programming Language :: Python :: 3
Classifier: Programming Language :: Python :: 3.7
